aheadworks_bitbucket_manager/__init__.py
aheadworks_bitbucket_manager/__main__.py
aheadworks_bitbucket_manager/api/__init__.py
aheadworks_bitbucket_manager/api/bitbucket_api_manager.py
aheadworks_bitbucket_manager/api/db_manager.py
aheadworks_bitbucket_manager/api/dockerhub_api_manager.py
aheadworks_bitbucket_manager/api/file_manager.py
aheadworks_bitbucket_manager/api/version_control_manager.py
aheadworks_bitbucket_manager/console/console.py
aheadworks_bitbucket_manager/model/__init__.py
aheadworks_bitbucket_manager/model/logging.py
aheadworks_bitbucket_manager/model/ssh_manager.py
aheadworks_bitbucket_manager/model/data/__init__.py
aheadworks_bitbucket_manager/model/data/bitbucket.py
aheadworks_bitbucket_manager/model/data/dockerhub.py
aheadworks_bitbucket_manager/model/parser/php.py
aheadworks_composer_manager/__init__.py
aheadworks_composer_manager/__main__.py
aheadworks_composer_manager/model/extension.py
aheadworks_composer_manager/model/package.py
aheadworks_composer_manager/service/resolver.py
aheadworks_composer_manager/storage/package.py
aheadworks_core/__init__.py
aheadworks_core/__main__.py
aheadworks_core/api/__init__.py
aheadworks_core/api/composer_manager.py
aheadworks_core/api/discord_api_manager.py
aheadworks_core/api/file_manager.py
aheadworks_core/api/jira_api_manager.py
aheadworks_core/api/magento_manager.py
aheadworks_core/api/teamwork_manager.py
aheadworks_core/console/console.py
aheadworks_core/model/__init__.py
aheadworks_core/model/cd.py
aheadworks_core/model/data/__init__.py
aheadworks_core/model/data/data_object.py
aheadworks_core/model/data/jira.py
aheadworks_core/model/data/teamwork.py
aheadworks_core/model/http/__init__.py
aheadworks_core/model/http/api_request.py
aheadworks_core/model/parser/json.py
aheadworks_core/model/parser/xml.py
aheadworks_release_manager/__init__.py
aheadworks_release_manager/__main__.py
aheadworks_release_manager/api/pipeline_manager.py
aheadworks_release_manager/api/release_manager.py
aheadworks_deploy_manager-1.8.20.dist-info/METADATA
aheadworks_deploy_manager-1.8.20.dist-info/WHEEL
aheadworks_deploy_manager-1.8.20.dist-info/top_level.txt
aheadworks_deploy_manager-1.8.20.dist-info/zip-safe
aheadworks_deploy_manager-1.8.20.dist-info/RECORD
